odmetrics/__init__.py
odmetrics/eval_many.py
odmetrics/evaluate.py
odmetrics/parse.py
odmetrics/track_compose.py
odmetrics/utils.py
odmetrics/_internal/__init__.py
odmetrics/_internal/_assign.py
odmetrics/_internal/_configs.py
odmetrics/_internal/_functools.py
odmetrics/_internal/_std.py
odmetrics/_internal/_track_tools.py
odmetrics/_internal/_typing.py
odmetrics/gt_info/.DS_Store
odmetrics/gt_info/gt_path.txt
odmetrics/gt_info/gt/HHPLT-1319.pkl
odmetrics/gt_info/gt/HHPLT-1347.pkl
odmetrics/gt_info/gt/HHPLT-1349.pkl
odmetrics/gt_info/gt/HHPLT-1351.pkl
odmetrics/gt_info/gt/HHPLT-1352.pkl
odmetrics/gt_info/gt/HHPLT-1353.pkl
odmetrics/gt_info/gt/HHPLT-1355.pkl
odmetrics/gt_info/gt/HHPLT-1356.pkl
odmetrics/metrics/__init__.py
odmetrics/metrics/_utils.py
odmetrics/metrics/base_metric.py
odmetrics/metrics/base_motmetric.py
odmetrics/metrics/metric_compose.py
odmetrics/metrics/mot_metrics.py
odmetrics/visual_tools/__init__.py
odmetrics/visual_tools/_utils.py
odmetrics/visual_tools/base_visual.py
odmetrics/visual_tools/image_visual.py
odmetrics/visual_tools/video_visual.py
hx_odmetrics-0.1.5.dist-info/LICENSE
hx_odmetrics-0.1.5.dist-info/METADATA
hx_odmetrics-0.1.5.dist-info/WHEEL
hx_odmetrics-0.1.5.dist-info/top_level.txt
hx_odmetrics-0.1.5.dist-info/RECORD
