Metadata-Version: 2.1
Name: hx-odmetrics
Version: 0.1.5
Summary: Multi-object Tracking (MOT) for perceptionn OD(Obstacle Detection), used for overall evaluation of E2E Tracking system.
Author: Haokun Zhang
Author-email: haokun.zhang@hirain.com
License: GNU General Public License v3 (GPLv3)
Requires-Python: >=3.7
License-File: LICENSE
Requires-Dist: numpy (>=1.22.0)
Requires-Dist: typing (>=3.5.0)
Requires-Dist: scipy (>=1.10.0)
Requires-Dist: motmetrics (>=1.3.0)
Requires-Dist: tqdm (>=4.62.0)
Requires-Dist: pillow (>=9.0.0)
Requires-Dist: cyber-record (~=0.1.12)
Requires-Dist: pandas (>=1.4.0)
